[{"id":"5529ca1b-649c-4ec3-abc6-1ca524b30260","name":"Clayborne","email":"cfitzharris0@army.mil","password":"f2ZXr2czlq","driver_license":"797-87-2965","avatar":"","admin":false,"created_at":"2021-11-05 06:04:54.000"},
{"id":"85d3b7c9-0c0b-4dc3-bb23-5d563256fd85","name":"Clary","email":"chunnawill1@so-net.ne.jp","password":"WEKTOUgmmYc","driver_license":"228-06-4245","avatar":"","admin":true,"created_at":"2022-06-27 20:56:06.000"},
{"id":"fc75f682-597e-43a4-a550-1df57d30c31b","name":"Ernest","email":"eespinoy2@deviantart.com","password":"pvrcdC","driver_license":"825-24-4315","avatar":"","admin":false,"created_at":"2021-10-12 00:04:10.000"},
{"id":"6713e1f6-b4c9-4212-b3fd-84fa58bdd507","name":"Kerry","email":"kmaccrackan3@theguardian.com","password":"zeqHj5O","driver_license":"847-55-7066","avatar":"","admin":true,"created_at":"2021-10-07 06:59:55.000"},
{"id":"65a2e5b7-4fc0-4e4e-b3f3-ed3c97e89967","name":"Nadeen","email":"nstuttard4@thetimes.co.uk","password":"LoDIBwct","driver_license":"443-49-6646","avatar":"","admin":true,"created_at":"2022-03-07 01:08:07.000"},
{"id":"9ea506cb-75f0-42f1-837e-991c9b346729","name":"Abbie","email":"awilmott5@meetup.com","password":"HBM83y1","driver_license":"332-21-6386","avatar":"","admin":true,"created_at":"2022-05-01 09:20:44.000"},
{"id":"e66a6855-1132-4bd0-9f3e-3fc3256ec27e","name":"Juline","email":"jfitzsymon6@360.cn","password":"YTwfINyDli","driver_license":"243-29-1691","avatar":"","admin":true,"created_at":"2021-12-14 10:26:54.000"},
{"id":"bdb5b8f1-4c8c-45a6-9bb4-a18db3921f0f","name":"Filide","email":"frottery7@theglobeandmail.com","password":"CFx0yMkyqN","driver_license":"545-26-0321","avatar":"","admin":false,"created_at":"2021-08-25 16:26:48.000"},
{"id":"5dc55602-611f-4b7c-8945-8ab5db950cbc","name":"Austin","email":"adonegan8@163.com","password":"pfBzvTZMI7Ve","driver_license":"117-18-3062","avatar":"","admin":false,"created_at":"2022-04-13 07:16:51.000"},
{"id":"dbebedd6-c201-47f7-9d72-5d992cbb751e","name":"Brittan","email":"bcowey9@pen.io","password":"Z2MvXV3U","driver_license":"660-51-6350","avatar":"","admin":false,"created_at":"2022-04-14 20:54:08.000"}]